pytest_accept/__init__.py
pytest_accept/assert_plugin.py
pytest_accept/common.py
pytest_accept/doctest_plugin.py
pytest_accept/tests/__init__.py
pytest_accept/tests/test_api_compatibility.py
pytest_accept/tests/test_assert_plugin.py
pytest_accept/tests/test_assertion_filtering.py
pytest_accept/tests/test_atomic_write_verification.py
pytest_accept/tests/test_complex_assertion_warning.py
pytest_accept/tests/test_concurrent_execution.py
pytest_accept/tests/test_doctest.py
pytest_accept/tests/test_doctest_formatting.py
pytest_accept/tests/test_file_change_detection.py
pytest_accept/tests/test_integration.py
pytest_accept/tests/test_multiple_doctest_failures.py
pytest_accept/tests/test_no_xdist.py
pytest_accept/tests/test_parametrized.py
pytest_accept/tests/test_unified_integration.py
pytest_accept-0.2.2.dist-info/WHEEL
pytest_accept-0.2.2.dist-info/entry_points.txt
pytest_accept-0.2.2.dist-info/METADATA
pytest_accept-0.2.2.dist-info/RECORD
