Metadata-Version: 2.4
Name: pytest-accept
Version: 0.2.2
Author: Maximilian Roos
Author-email: Maximilian Roos <m@maxroos.com>
License-Expression: Apache-2.0
Requires-Dist: astor>=0.8.1
Requires-Dist: pytest>=7
Requires-Python: >=3.9, <4
Project-URL: homepage, https://github.com/max-sixty/pytest-accept
Project-URL: repository, https://github.com/max-sixty/pytest-accept
